beanhub_cli/__init__.py
beanhub_cli/aliase.py
beanhub_cli/api_helpers.py
beanhub_cli/auth.py
beanhub_cli/cli.py
beanhub_cli/config.py
beanhub_cli/encryption.py
beanhub_cli/environment.py
beanhub_cli/file_io.py
beanhub_cli/format.py
beanhub_cli/import_cli.py
beanhub_cli/login.py
beanhub_cli/main.py
beanhub_cli/connect/__init__.py
beanhub_cli/connect/cli.py
beanhub_cli/connect/main.py
beanhub_cli/forms/__init__.py
beanhub_cli/forms/cli.py
beanhub_cli/forms/main.py
beanhub_cli/forms/validator.py
beanhub_cli/forms/app/__init__.py
beanhub_cli/forms/app/constants.py
beanhub_cli/forms/app/deps.py
beanhub_cli/forms/app/helpers.py
beanhub_cli/forms/app/main.py
beanhub_cli/forms/app/routes.py
beanhub_cli/forms/app/settings.py
beanhub_cli/forms/app/data/sample_forms_doc.yaml
beanhub_cli/forms/app/static/js/beanhub-web-react-0.3.0.js
beanhub_cli/forms/app/static/js/beanhub-web-react-0.3.0.js.LICENSE.txt
beanhub_cli/forms/app/static/js/beanhub-web-react-0.3.0.js.map
beanhub_cli/forms/app/static/vendor/bootstrap-datepicker/LICENSE
beanhub_cli/forms/app/static/vendor/bootstrap-datepicker/css/bootstrap-datepicker.css
beanhub_cli/forms/app/static/vendor/bootstrap-datepicker/css/bootstrap-datepicker.css.map
beanhub_cli/forms/app/static/vendor/bootstrap-datepicker/css/bootstrap-datepicker.min.css
beanhub_cli/forms/app/static/vendor/bootstrap-datepicker/js/bootstrap-datepicker.js
beanhub_cli/forms/app/static/vendor/bootstrap-datepicker/js/bootstrap-datepicker.min.js
beanhub_cli/forms/app/static/vendor/bootstrap-datepicker/locales/bootstrap-datepicker-en-CA.min.js
beanhub_cli/forms/app/static/vendor/bootstrap-datepicker/locales/bootstrap-datepicker.ar-DZ.min.js
beanhub_cli/forms/app/static/vendor/bootstrap-datepicker/locales/bootstrap-datepicker.ar-tn.min.js
beanhub_cli/forms/app/static/vendor/bootstrap-datepicker/locales/bootstrap-datepicker.ar.min.js
beanhub_cli/forms/app/static/vendor/bootstrap-datepicker/locales/bootstrap-datepicker.az.min.js
beanhub_cli-3.1.0.dist-info/METADATA
beanhub_cli-3.1.0.dist-info/WHEEL
beanhub_cli-3.1.0.dist-info/entry_points.txt
beanhub_cli-3.1.0.dist-info/licenses/LICENSE
beanhub_cli-3.1.0.dist-info/RECORD
