Metadata-Version: 2.4
Name: beanhub-cli
Version: 3.1.0
Summary: Command line tools for BeanHub and Beancount users
Project-URL: Documentation, https://beanhub-cli-docs.beanhub.io
Author-email: Fang-Pen Lin <fangpen@launchplatform.com>
License-Expression: MIT
License-File: LICENSE
Requires-Python: ~=3.10
Requires-Dist: attrs>=22.2.0
Requires-Dist: beancount-black<2,>=1.0.1
Requires-Dist: beancount-data>=3.0.2
Requires-Dist: beancount-exporter>=3.0.0
Requires-Dist: beancount-parser<1.3.0,>=1.2.3
Requires-Dist: beanhub-extract<1.0.0,>=0.1.0
Requires-Dist: beanhub-forms<0.2,>=0.1.3
Requires-Dist: beanhub-import<2.0.0,>=1.0.0
Requires-Dist: beanhub-inbox<0.3.0,>=0.2.3
Requires-Dist: click<9,>=8.1.7
Requires-Dist: cryptography>=44.0.0
Requires-Dist: fastapi-mcp>=0.3.7
Requires-Dist: fastapi<1.0.0,>=0.98.0
Requires-Dist: httpx<0.29.0,>=0.20.0
Requires-Dist: jinja2<4.0.0,>=3.1.2
Requires-Dist: orjson>=3.11.0
Requires-Dist: pydantic-settings<3,>=2.0.3
Requires-Dist: pydantic<3,>=2.4.0
Requires-Dist: pynacl<2,>=1.5.0
Requires-Dist: python-dateutil<3,>=2.8.0
Requires-Dist: pyyaml<7,>=6.0.1
Requires-Dist: rich<14,>=13.6.0
Requires-Dist: starlette-wtf<0.5,>=0.4.3
Requires-Dist: tomli-w<2,>=1.1.0
Requires-Dist: tomli<3,>=2.2.1
Requires-Dist: uvicorn<1.0.0,>=0.23.2
